gapcheck/__init__.py
gapcheck/buildparser.py
gapcheck/gap.py
gapcheck/gapcheck.py
gapcheck/join.py
gapcheck/log.py
gapcheck/reverse.py
gapcheck/tags.py
gapcheck-0.10.1.dist-info/DESCRIPTION.rst
gapcheck-0.10.1.dist-info/METADATA
gapcheck-0.10.1.dist-info/RECORD
gapcheck-0.10.1.dist-info/WHEEL
gapcheck-0.10.1.dist-info/entry_points.txt
gapcheck-0.10.1.dist-info/metadata.json
gapcheck-0.10.1.dist-info/top_level.txt
tests/__init__.py
tests/test_gapcheck.py
tests/test_join.py
tests/test_reverse.py
