Metadata-Version: 2.0
Name: gapcheck
Version: 0.10.1
Summary: Check gap between tracks
Home-page: https://bitbucket.com/penicolas/gapcheck
Author: penicolas
Author-email: png1981@gmail.com
License: UNKNOWN
Platform: UNKNOWN
Classifier: Programming Language :: Python
Classifier: Development Status :: 4 - Beta
Classifier: License :: OSI Approved :: MIT License
Classifier: Operating System :: OS Independent
Classifier: Programming Language :: Python :: 3 :: Only
Classifier: Topic :: Utilities
Requires-Dist: mutagen
Requires-Dist: sox
